reflex_swipe/__init__.py
reflex_swipe-1.1.2.dist-info/METADATA
reflex_swipe-1.1.2.dist-info/WHEEL
reflex_swipe-1.1.2.dist-info/RECORD
