Metadata-Version: 2.4
Name: reflex-swipe
Version: 1.1.2
Summary: Provides swipe gestures detections for reflex apps.
Project-URL: repository, https://github.com/adhami3310/reflex-swipe
Author-email: Khaleel Al-Adhami <khaleel.aladhami@gmail.com>
License: MIT
Keywords: reflex,reflex-custom-components
Requires-Python: >=3.10
Requires-Dist: reflex>=0.7.11
